<?xml version='1.0' encoding='UTF-8' standalone='yes' ?>
<hierarchy rotation="0">
    <node index="0" text="" resource-id="" class="android.widget.FrameLayout" package="com.android.documentsui" content-desc="" checkable="false" checked="false" clickable="false" enabled="true" focusable="false" focused="false" scrollable="false" long-clickable="false" password="false" selected="false" bounds="[0,0][1080,1794]">
        <node index="0" text="" resource-id="" class="android.widget.FrameLayout" package="com.android.documentsui" content-desc="" checkable="false" checked="false" clickable="false" enabled="true" focusable="false" focused="false" scrollable="false" long-clickable="false" password="false" selected="false" bounds="[0,0][1080,1794]">
            <node index="0" text="" resource-id="android:id/content" class="android.widget.FrameLayout" package="com.android.documentsui" content-desc="" checkable="false" checked="false" clickable="false" enabled="true" focusable="false" focused="false" scrollable="false" long-clickable="false" password="false" selected="false" bounds="[0,63][1080,1794]">
                <node index="0" text="" resource-id="com.android.documentsui:id/coordinator_layout" class="android.view.ViewGroup" package="com.android.documentsui" content-desc="" checkable="false" checked="false" clickable="false" enabled="true" focusable="false" focused="false" scrollable="false" long-clickable="false" password="false" selected="false" bounds="[0,63][1080,1794]">
                    <node index="0" text="" resource-id="com.android.documentsui:id/drawer_layout" class="android.support.v4.widget.DrawerLayout" package="com.android.documentsui" content-desc="" checkable="false" checked="false" clickable="false" enabled="true" focusable="false" focused="false" scrollable="false" long-clickable="false" password="false" selected="false" bounds="[0,63][1080,1794]">
                        <node index="0" text="" resource-id="" class="android.widget.LinearLayout" package="com.android.documentsui" content-desc="" checkable="false" checked="false" clickable="false" enabled="true" focusable="false" focused="false" scrollable="false" long-clickable="false" password="false" selected="false" bounds="[0,63][1080,1794]">
                            <node index="0" text="" resource-id="com.android.documentsui:id/toolbar" class="android.view.ViewGroup" package="com.android.documentsui" content-desc="" checkable="false" checked="false" clickable="false" enabled="true" focusable="false" focused="false" scrollable="false" long-clickable="false" password="false" selected="false" bounds="[0,63][1080,210]">
                                <node index="0" text="" resource-id="" class="android.widget.ImageButton" package="com.android.documentsui" content-desc="Show roots" checkable="false" checked="false" clickable="true" enabled="true" focusable="true" focused="false" scrollable="false" long-clickable="false" password="false" selected="false" bounds="[0,63][147,210]" />
                                <node index="1" text="Downloads" resource-id="" class="android.widget.TextView" package="com.android.documentsui" content-desc="" checkable="false" checked="false" clickable="false" enabled="true" focusable="false" focused="false" scrollable="false" long-clickable="false" password="false" selected="false" bounds="[189,101][452,172]" />
                                <node index="2" text="" resource-id="" class="android.widget.LinearLayout" package="com.android.documentsui" content-desc="" checkable="false" checked="false" clickable="false" enabled="true" focusable="false" focused="false" scrollable="false" long-clickable="false" password="false" selected="false" bounds="[723,63][1080,210]">
                                    <node index="0" text="" resource-id="com.android.documentsui:id/option_menu_search" class="android.widget.TextView" package="com.android.documentsui" content-desc="Search" checkable="false" checked="false" clickable="true" enabled="true" focusable="true" focused="false" scrollable="false" long-clickable="false" password="false" selected="false" bounds="[723,73][849,199]" />
                                    <node index="1" text="" resource-id="com.android.documentsui:id/option_menu_grid" class="android.widget.TextView" package="com.android.documentsui" content-desc="Grid view" checkable="false" checked="false" clickable="true" enabled="true" focusable="true" focused="false" scrollable="false" long-clickable="false" password="false" selected="false" bounds="[849,73][975,199]" />
                                    <node index="2" text="" resource-id="" class="android.widget.ImageButton" package="com.android.documentsui" content-desc="More options" checkable="false" checked="false" clickable="true" enabled="true" focusable="true" focused="false" scrollable="false" long-clickable="true" password="false" selected="false" bounds="[975,73][1080,199]" />
                                </node>
                            </node>
                            <node index="1" text="" resource-id="" class="android.widget.FrameLayout" package="com.android.documentsui" content-desc="" checkable="false" checked="false" clickable="false" enabled="true" focusable="false" focused="false" scrollable="false" long-clickable="false" password="false" selected="false" bounds="[0,210][1080,1794]">
                                <node index="0" text="" resource-id="" class="android.widget.LinearLayout" package="com.android.documentsui" content-desc="" checkable="false" checked="false" clickable="false" enabled="true" focusable="false" focused="false" scrollable="false" long-clickable="false" password="false" selected="false" bounds="[0,210][1080,1794]">
                                    <node index="0" text="" resource-id="com.android.documentsui:id/dropdown_sort_widget" class="android.widget.LinearLayout" package="com.android.documentsui" content-desc="" checkable="false" checked="false" clickable="false" enabled="true" focusable="false" focused="false" scrollable="false" long-clickable="false" password="false" selected="false" bounds="[0,210][1080,368]">
                                        <node index="0" text="Modified" resource-id="com.android.documentsui:id/sort_dimen_dropdown" class="android.widget.TextView" package="com.android.documentsui" content-desc="" checkable="false" checked="false" clickable="true" enabled="true" focusable="true" focused="false" scrollable="false" long-clickable="false" password="false" selected="false" bounds="[661,226][911,352]" />
                                        <node index="1" text="" resource-id="com.android.documentsui:id/sort_arrow" class="android.widget.ImageView" package="com.android.documentsui" content-desc="Descending" checkable="false" checked="false" clickable="true" enabled="true" focusable="true" focused="false" scrollable="false" long-clickable="false" password="false" selected="false" bounds="[922,226][1048,352]" />
                                    </node>
                                    <node index="1" text="" resource-id="com.android.documentsui:id/container_directory" class="android.widget.FrameLayout" package="com.android.documentsui" content-desc="" checkable="false" checked="false" clickable="false" enabled="true" focusable="false" focused="false" scrollable="false" long-clickable="false" password="false" selected="false" bounds="[0,368][1080,1794]">
                                        <node index="0" text="" resource-id="" class="android.widget.LinearLayout" package="com.android.documentsui" content-desc="" checkable="false" checked="false" clickable="false" enabled="true" focusable="false" focused="false" scrollable="false" long-clickable="false" password="false" selected="false" bounds="[0,368][1080,1794]">
                                            <node index="0" text="" resource-id="com.android.documentsui:id/refresh_layout" class="android.view.ViewGroup" package="com.android.documentsui" content-desc="" checkable="false" checked="false" clickable="false" enabled="true" focusable="false" focused="false" scrollable="false" long-clickable="false" password="false" selected="false" bounds="[0,368][1080,1794]">
                                                <node index="0" text="" resource-id="com.android.documentsui:id/dir_list" class="android.support.v7.widget.RecyclerView" package="com.android.documentsui" content-desc="" checkable="false" checked="false" clickable="false" enabled="true" focusable="true" focused="false" scrollable="false" long-clickable="false" password="false" selected="false" bounds="[0,368][1080,1794]">
                                                    <node index="0" text="" resource-id="android:id/empty" class="android.widget.FrameLayout" package="com.android.documentsui" content-desc="" checkable="false" checked="false" clickable="true" enabled="true" focusable="true" focused="false" scrollable="false" long-clickable="false" password="false" selected="false" bounds="[0,368][1080,1794]">
                                                        <node index="0" text="" resource-id="com.android.documentsui:id/content" class="android.widget.RelativeLayout" package="com.android.documentsui" content-desc="" checkable="false" checked="false" clickable="false" enabled="true" focusable="false" focused="false" scrollable="false" long-clickable="false" password="false" selected="false" bounds="[0,368][1080,1794]">
                                                            <node index="0" text="" resource-id="com.android.documentsui:id/artwork" class="android.widget.ImageView" package="com.android.documentsui" content-desc="" checkable="false" checked="false" clickable="false" enabled="true" focusable="false" focused="false" scrollable="false" long-clickable="false" password="false" selected="false" bounds="[0,691][1080,1347]" />
                                                            <node index="1" text="No items" resource-id="com.android.documentsui:id/message" class="android.widget.TextView" package="com.android.documentsui" content-desc="" checkable="false" checked="false" clickable="false" enabled="true" focusable="false" focused="false" scrollable="false" long-clickable="false" password="false" selected="false" bounds="[455,1413][624,1470]" />
                                                        </node>
                                                    </node>
                                                </node>
                                            </node>
                                        </node>
                                    </node>
                                </node>
                                <node index="1" text="" resource-id="com.android.documentsui:id/drawer_edge" class="android.view.View" package="com.android.documentsui" content-desc="" checkable="false" checked="false" clickable="false" enabled="true" focusable="false" focused="false" scrollable="false" long-clickable="false" password="false" selected="false" bounds="[0,210][32,1794]" />
                            </node>
                        </node>
                        <node index="1" text="" resource-id="com.android.documentsui:id/drawer_roots" class="android.widget.LinearLayout" package="com.android.documentsui" content-desc="" checkable="false" checked="false" clickable="false" enabled="true" focusable="false" focused="false" scrollable="false" long-clickable="false" password="false" selected="false" bounds="[0,63][735,1794]">
                            <node index="0" text="" resource-id="com.android.documentsui:id/roots_toolbar" class="android.view.ViewGroup" package="com.android.documentsui" content-desc="" checkable="false" checked="false" clickable="false" enabled="true" focusable="false" focused="false" scrollable="false" long-clickable="false" password="false" selected="false" bounds="[0,63][735,210]">
                                <node index="0" text="Files" resource-id="" class="android.widget.TextView" package="com.android.documentsui" content-desc="" checkable="false" checked="false" clickable="false" enabled="true" focusable="false" focused="false" scrollable="false" long-clickable="false" password="false" selected="false" bounds="[42,101][154,172]" />
                            </node>
                            <node index="1" text="" resource-id="com.android.documentsui:id/container_roots" class="android.widget.FrameLayout" package="com.android.documentsui" content-desc="" checkable="false" checked="false" clickable="false" enabled="true" focusable="false" focused="false" scrollable="false" long-clickable="false" password="false" selected="false" bounds="[0,210][735,1794]">
                                <node index="0" text="" resource-id="com.android.documentsui:id/roots_list" class="android.widget.ListView" package="com.android.documentsui" content-desc="" checkable="false" checked="false" clickable="false" enabled="true" focusable="true" focused="false" scrollable="false" long-clickable="false" password="false" selected="false" bounds="[0,210][735,1794]">
                                    <node index="0" text="" resource-id="" class="android.widget.LinearLayout" package="com.android.documentsui" content-desc="" checkable="false" checked="false" clickable="false" enabled="true" focusable="false" focused="false" scrollable="false" long-clickable="false" password="false" selected="false" bounds="[0,231][735,357]">
                                        <node index="0" text="" resource-id="" class="android.widget.FrameLayout" package="com.android.documentsui" content-desc="" checkable="false" checked="false" clickable="false" enabled="true" focusable="false" focused="false" scrollable="false" long-clickable="false" password="false" selected="false" bounds="[64,241][169,346]">
                                            <node index="0" text="" resource-id="android:id/icon" class="android.widget.ImageView" package="com.android.documentsui" content-desc="" checkable="false" checked="false" clickable="false" enabled="true" focusable="false" focused="false" scrollable="false" long-clickable="false" password="false" selected="false" bounds="[64,241][127,346]" />
                                        </node>
                                        <node index="1" text="" resource-id="" class="android.widget.LinearLayout" package="com.android.documentsui" content-desc="" checkable="false" checked="false" clickable="false" enabled="true" focusable="false" focused="false" scrollable="false" long-clickable="false" password="false" selected="false" bounds="[169,247][630,340]">
                                            <node index="0" text="Images" resource-id="android:id/title" class="android.widget.TextView" package="com.android.documentsui" content-desc="" checkable="false" checked="false" clickable="false" enabled="true" focusable="false" focused="false" scrollable="false" long-clickable="false" password="false" selected="false" bounds="[211,268][630,319]" />
                                        </node>
                                        <node index="2" text="" resource-id="" class="android.widget.FrameLayout" package="com.android.documentsui" content-desc="" checkable="false" checked="false" clickable="false" enabled="true" focusable="false" focused="false" scrollable="false" long-clickable="false" password="false" selected="false" bounds="[630,241][735,346]" />
                                    </node>
                                    <node index="1" text="" resource-id="" class="android.widget.LinearLayout" package="com.android.documentsui" content-desc="" checkable="false" checked="false" clickable="false" enabled="true" focusable="false" focused="false" scrollable="false" long-clickable="false" password="false" selected="false" bounds="[0,357][735,483]">
                                        <node index="0" text="" resource-id="" class="android.widget.FrameLayout" package="com.android.documentsui" content-desc="" checkable="false" checked="false" clickable="false" enabled="true" focusable="false" focused="false" scrollable="false" long-clickable="false" password="false" selected="false" bounds="[64,367][169,472]">
                                            <node index="0" text="" resource-id="android:id/icon" class="android.widget.ImageView" package="com.android.documentsui" content-desc="" checkable="false" checked="false" clickable="false" enabled="true" focusable="false" focused="false" scrollable="false" long-clickable="false" password="false" selected="false" bounds="[64,367][127,472]" />
                                        </node>
                                        <node index="1" text="" resource-id="" class="android.widget.LinearLayout" package="com.android.documentsui" content-desc="" checkable="false" checked="false" clickable="false" enabled="true" focusable="false" focused="false" scrollable="false" long-clickable="false" password="false" selected="false" bounds="[169,373][630,466]">
                                            <node index="0" text="Videos" resource-id="android:id/title" class="android.widget.TextView" package="com.android.documentsui" content-desc="" checkable="false" checked="false" clickable="false" enabled="true" focusable="false" focused="false" scrollable="false" long-clickable="false" password="false" selected="false" bounds="[211,394][630,445]" />
                                        </node>
                                        <node index="2" text="" resource-id="" class="android.widget.FrameLayout" package="com.android.documentsui" content-desc="" checkable="false" checked="false" clickable="false" enabled="true" focusable="false" focused="false" scrollable="false" long-clickable="false" password="false" selected="false" bounds="[630,367][735,472]" />
                                    </node>
                                    <node index="2" text="" resource-id="" class="android.widget.LinearLayout" package="com.android.documentsui" content-desc="" checkable="false" checked="false" clickable="false" enabled="true" focusable="false" focused="false" scrollable="false" long-clickable="false" password="false" selected="false" bounds="[0,483][735,609]">
                                        <node index="0" text="" resource-id="" class="android.widget.FrameLayout" package="com.android.documentsui" content-desc="" checkable="false" checked="false" clickable="false" enabled="true" focusable="false" focused="false" scrollable="false" long-clickable="false" password="false" selected="false" bounds="[64,493][169,598]">
                                            <node index="0" text="" resource-id="android:id/icon" class="android.widget.ImageView" package="com.android.documentsui" content-desc="" checkable="false" checked="false" clickable="false" enabled="true" focusable="false" focused="false" scrollable="false" long-clickable="false" password="false" selected="false" bounds="[64,493][127,598]" />
                                        </node>
                                        <node index="1" text="" resource-id="" class="android.widget.LinearLayout" package="com.android.documentsui" content-desc="" checkable="false" checked="false" clickable="false" enabled="true" focusable="false" focused="false" scrollable="false" long-clickable="false" password="false" selected="false" bounds="[169,499][630,592]">
                                            <node index="0" text="Audio" resource-id="android:id/title" class="android.widget.TextView" package="com.android.documentsui" content-desc="" checkable="false" checked="false" clickable="false" enabled="true" focusable="false" focused="false" scrollable="false" long-clickable="false" password="false" selected="false" bounds="[211,520][630,571]" />
                                        </node>
                                        <node index="2" text="" resource-id="" class="android.widget.FrameLayout" package="com.android.documentsui" content-desc="" checkable="false" checked="false" clickable="false" enabled="true" focusable="false" focused="false" scrollable="false" long-clickable="false" password="false" selected="false" bounds="[630,493][735,598]" />
                                    </node>
                                    <node index="3" text="" resource-id="" class="android.widget.LinearLayout" package="com.android.documentsui" content-desc="" checkable="false" checked="false" clickable="false" enabled="true" focusable="false" focused="false" scrollable="false" long-clickable="false" password="false" selected="false" bounds="[0,609][735,735]">
                                        <node index="0" text="" resource-id="" class="android.widget.FrameLayout" package="com.android.documentsui" content-desc="" checkable="false" checked="false" clickable="false" enabled="true" focusable="false" focused="false" scrollable="false" long-clickable="false" password="false" selected="false" bounds="[64,619][169,724]">
                                            <node index="0" text="" resource-id="android:id/icon" class="android.widget.ImageView" package="com.android.documentsui" content-desc="" checkable="false" checked="false" clickable="false" enabled="true" focusable="false" focused="false" scrollable="false" long-clickable="false" password="false" selected="false" bounds="[64,619][127,724]" />
                                        </node>
                                        <node index="1" text="" resource-id="" class="android.widget.LinearLayout" package="com.android.documentsui" content-desc="" checkable="false" checked="false" clickable="false" enabled="true" focusable="false" focused="false" scrollable="false" long-clickable="false" password="false" selected="false" bounds="[169,625][630,718]">
                                            <node index="0" text="Recent" resource-id="android:id/title" class="android.widget.TextView" package="com.android.documentsui" content-desc="" checkable="false" checked="false" clickable="false" enabled="true" focusable="false" focused="false" scrollable="false" long-clickable="false" password="false" selected="false" bounds="[211,646][630,697]" />
                                        </node>
                                        <node index="2" text="" resource-id="" class="android.widget.FrameLayout" package="com.android.documentsui" content-desc="" checkable="false" checked="false" clickable="false" enabled="true" focusable="false" focused="false" scrollable="false" long-clickable="false" password="false" selected="false" bounds="[630,619][735,724]" />
                                    </node>
                                    <node index="4" text="" resource-id="" class="android.widget.FrameLayout" package="com.android.documentsui" content-desc="" checkable="false" checked="false" clickable="false" enabled="true" focusable="false" focused="false" scrollable="false" long-clickable="false" password="false" selected="false" bounds="[0,735][735,802]">
                                        <node index="0" text="" resource-id="" class="android.view.View" package="com.android.documentsui" content-desc="" checkable="false" checked="false" clickable="false" enabled="true" focusable="false" focused="false" scrollable="false" long-clickable="false" password="false" selected="false" bounds="[0,767][735,770]" />
                                    </node>
                                    <node index="5" text="" resource-id="" class="android.widget.LinearLayout" package="com.android.documentsui" content-desc="" checkable="false" checked="false" clickable="false" enabled="true" focusable="false" focused="false" scrollable="false" long-clickable="false" password="false" selected="false" bounds="[0,802][735,928]">
                                        <node index="0" text="" resource-id="" class="android.widget.FrameLayout" package="com.android.documentsui" content-desc="" checkable="false" checked="false" clickable="false" enabled="true" focusable="false" focused="false" scrollable="false" long-clickable="false" password="false" selected="false" bounds="[64,812][169,917]">
                                            <node index="0" text="" resource-id="android:id/icon" class="android.widget.ImageView" package="com.android.documentsui" content-desc="" checkable="false" checked="false" clickable="false" enabled="true" focusable="false" focused="false" scrollable="false" long-clickable="false" password="false" selected="false" bounds="[64,812][127,917]" />
                                        </node>
                                        <node index="1" text="" resource-id="" class="android.widget.LinearLayout" package="com.android.documentsui" content-desc="" checkable="false" checked="false" clickable="false" enabled="true" focusable="false" focused="false" scrollable="false" long-clickable="false" password="false" selected="false" bounds="[169,818][630,911]">
                                            <node index="0" text="Downloads" resource-id="android:id/title" class="android.widget.TextView" package="com.android.documentsui" content-desc="" checkable="false" checked="false" clickable="false" enabled="true" focusable="false" focused="false" scrollable="false" long-clickable="false" password="false" selected="false" bounds="[211,839][630,890]" />
                                        </node>
                                        <node index="2" text="" resource-id="" class="android.widget.FrameLayout" package="com.android.documentsui" content-desc="" checkable="false" checked="false" clickable="false" enabled="true" focusable="false" focused="false" scrollable="false" long-clickable="false" password="false" selected="false" bounds="[630,812][735,917]" />
                                    </node>
                                    <node index="6" text="" resource-id="" class="android.widget.LinearLayout" package="com.android.documentsui" content-desc="" checkable="false" checked="false" clickable="false" enabled="true" focusable="false" focused="false" scrollable="false" long-clickable="false" password="false" selected="false" bounds="[0,928][735,1067]">
                                        <node index="0" text="" resource-id="" class="android.widget.FrameLayout" package="com.android.documentsui" content-desc="" checkable="false" checked="false" clickable="false" enabled="true" focusable="false" focused="false" scrollable="false" long-clickable="false" password="false" selected="false" bounds="[64,945][169,1050]">
                                            <node index="0" text="" resource-id="android:id/icon" class="android.widget.ImageView" package="com.android.documentsui" content-desc="" checkable="false" checked="false" clickable="false" enabled="true" focusable="false" focused="false" scrollable="false" long-clickable="false" password="false" selected="false" bounds="[64,945][127,1050]" />
                                        </node>
                                        <node index="1" text="" resource-id="" class="android.widget.LinearLayout" package="com.android.documentsui" content-desc="" checkable="false" checked="false" clickable="false" enabled="true" focusable="false" focused="false" scrollable="false" long-clickable="false" password="false" selected="false" bounds="[169,928][630,1067]">
                                            <node index="0" text="SDCARD" resource-id="android:id/title" class="android.widget.TextView" package="com.android.documentsui" content-desc="" checkable="false" checked="false" clickable="false" enabled="true" focusable="false" focused="false" scrollable="false" long-clickable="false" password="false" selected="false" bounds="[211,949][630,1000]" />
                                            <node index="1" text="535 MB free" resource-id="android:id/summary" class="android.widget.TextView" package="com.android.documentsui" content-desc="" checkable="false" checked="false" clickable="false" enabled="true" focusable="false" focused="false" scrollable="false" long-clickable="false" password="false" selected="false" bounds="[211,1000][630,1046]" />
                                        </node>
                                        <node index="2" text="" resource-id="" class="android.widget.FrameLayout" package="com.android.documentsui" content-desc="" checkable="false" checked="false" clickable="false" enabled="true" focusable="false" focused="false" scrollable="false" long-clickable="false" password="false" selected="false" bounds="[630,945][735,1050]">
                                            <node index="0" text="" resource-id="com.android.documentsui:id/eject_icon" class="android.widget.ImageView" package="com.android.documentsui" content-desc="Eject" checkable="false" checked="false" clickable="true" enabled="true" focusable="true" focused="false" scrollable="false" long-clickable="false" password="false" selected="false" bounds="[630,945][693,1050]" />
                                        </node>
                                    </node>
                                </node>
                            </node>
                        </node>
                    </node>
                </node>
            </node>
        </node>
        <node index="1" text="" resource-id="android:id/statusBarBackground" class="android.view.View" package="com.android.documentsui" content-desc="" checkable="false" checked="false" clickable="false" enabled="true" focusable="false" focused="false" scrollable="false" long-clickable="false" password="false" selected="false" bounds="[0,0][1080,63]" />
        <node index="2" text="" resource-id="android:id/navigationBarBackground" class="android.view.View" package="com.android.documentsui" content-desc="" checkable="false" checked="false" clickable="false" enabled="true" focusable="false" focused="false" scrollable="false" long-clickable="false" password="false" selected="false" bounds="[0,0][0,0]" />
    </node>
</hierarchy>